[{"__type__":"cc.Prefab","_name":"GameRoomItem","data":{"__id__":1}},{"__type__":"cc.Node","_name":"GameRoomItem","_children":[{"__id__":2},{"__id__":3},{"__id__":8}],"_components":[{"__type__":"cc.Button","node":{"__id__":1},"duration":0.2,"zoomScale":0.9,"_N$transition":3,"transition":3,"_N$target":{"__id__":1}},{"__type__":"2fe093uR5xFBJ45eAzvR13D","node":{"__id__":1},"teenpattiimgs":[{"__uuid__":"738vTx3qRJrYBRem3OABqM"},{"__uuid__":"b89vpakT9AE5Uop7zO6Vm2"},{"__uuid__":"ccy4KpWNdB67lyCCcBsQ4+"}]}],"_prefab":{"__type__":"cc.PrefabInfo","root":{"__id__":1},"asset":{"__uuid__":"cfdzJ7LI5Bt5E4IBjvAUry"},"fileId":"c6TE7Q6GZO84FNVmbUYcm2"},"_contentSize":{"__type__":"cc.Size","width":304,"height":394},"_trs":{"__type__":"TypedArray","ctor":"Float32Array","array":[640,360,0,0,0,0,1,1,1,0]}},{"__type__":"cc.Node","_name":"gameroomsprite","_parent":{"__id__":1},"_components":[{"__type__":"cc.Sprite","node":{"__id__":2},"_materials":[{"__uuid__":"ecpdLyjvZBwrvm+cedCcQy"}],"_sizeMode":0}],"_prefab":{"__type__":"cc.PrefabInfo","root":{"__id__":1},"asset":{"__uuid__":"cfdzJ7LI5Bt5E4IBjvAUry"},"fileId":"edewYP6MVCh7iiMANvnlXd"},"_contentSize":{"__type__":"cc.Size","width":304,"height":394},"_trs":{"__type__":"TypedArray","ctor":"Float32Array","array":[0,0,0,0,0,0,1,1,1,1]}},{"__type__":"cc.Node","_name":"minentryview","_parent":{"__id__":1},"_children":[{"__id__":4},{"__id__":5}],"_components":[{"__type__":"cc.Layout","node":{"__id__":3},"_layoutSize":{"__type__":"cc.Size","width":224.6,"height":30}},{"__type__":"cc.Widget","node":{"__id__":3},"_alignFlags":4,"_bottom":90.37300109863281}],"_prefab":{"__type__":"cc.PrefabInfo","root":{"__id__":1},"asset":{"__uuid__":"cfdzJ7LI5Bt5E4IBjvAUry"},"fileId":"f5m7h5MNJItpPQbmgJkG39"},"_contentSize":{"__type__":"cc.Size","width":224.6,"height":30},"_trs":{"__type__":"TypedArray","ctor":"Float32Array","array":[0,-91.62699890136719,0,0,0,0,1,1,1,1]}},{"__type__":"cc.Node","_name":"minidum_title","_parent":{"__id__":3},"_components":[{"__type__":"cc.Label","node":{"__id__":4},"_materials":[{"__uuid__":"ecpdLyjvZBwrvm+cedCcQy"}],"_string":"Min-Entry:","_N$string":"Min-Entry:","_fontSize":24,"_lineHeight":24},{"__type__":"cc.LabelOutline","node":{"__id__":4},"_color":{"__type__":"cc.Color","r":45,"g":7,"b":109},"_width":2.6},{"__type__":"cc.Widget","node":{"__id__":4},"_alignFlags":8,"_left":-0.0000015258789147765128}],"_prefab":{"__type__":"cc.PrefabInfo","root":{"__id__":1},"asset":{"__uuid__":"cfdzJ7LI5Bt5E4IBjvAUry"},"fileId":"32wxaKRUlMpLZ1sle21eTQ"},"_color":{"__type__":"cc.Color","r":255,"g":242,"b":34},"_contentSize":{"__type__":"cc.Size","width":114.55,"height":35.44},"_trs":{"__type__":"TypedArray","ctor":"Float32Array","array":[-55.025001525878906,0,0,0,0,0,1,1,1,1]}},{"__type__":"cc.Node","_name":"minentrylayout","_parent":{"__id__":3},"_children":[{"__id__":6},{"__id__":7}],"_components":[{"__type__":"cc.Layout","node":{"__id__":5},"_layoutSize":{"__type__":"cc.Size","width":43.15,"height":36},"_resize":1,"_N$layoutType":1,"_N$spacingX":4.6},{"__type__":"cc.Widget","node":{"__id__":5},"alignMode":2,"_alignFlags":32}],"_prefab":{"__type__":"cc.PrefabInfo","root":{"__id__":1},"asset":{"__uuid__":"cfdzJ7LI5Bt5E4IBjvAUry"},"fileId":"0bC/friadJqqMWmvggG0Uc"},"_contentSize":{"__type__":"cc.Size","width":43.15,"height":36},"_trs":{"__type__":"TypedArray","ctor":"Float32Array","array":[90.7249984741211,0,0,0,0,0,1,1,1,1]}},{"__type__":"cc.Node","_name":"jinbiimg","_parent":{"__id__":5},"_components":[{"__type__":"cc.Sprite","node":{"__id__":6},"_materials":[{"__uuid__":"ecpdLyjvZBwrvm+cedCcQy"}],"_spriteFrame":{"__uuid__":"85EDehklJElahVe84nelrT"}}],"_prefab":{"__type__":"cc.PrefabInfo","root":{"__id__":1},"asset":{"__uuid__":"cfdzJ7LI5Bt5E4IBjvAUry"},"fileId":"edHRD5OMVIE4LNYipPcIsD"},"_contentSize":{"__type__":"cc.Size","width":20,"height":20},"_trs":{"__type__":"TypedArray","ctor":"Float32Array","array":[-11.574999809265137,0,0,0,0,0,1,1,1,1]}},{"__type__":"cc.Node","_name":"minentry","_parent":{"__id__":5},"_components":[{"__type__":"cc.Label","node":{"__id__":7},"_materials":[{"__uuid__":"ecpdLyjvZBwrvm+cedCcQy"}],"_string":"1","_N$string":"1","_fontSize":24,"_lineHeight":24},{"__type__":"cc.LabelOutline","node":{"__id__":7},"_color":{"__type__":"cc.Color","r":45,"g":7,"b":109},"_width":2.6}],"_prefab":{"__type__":"cc.PrefabInfo","root":{"__id__":1},"asset":{"__uuid__":"cfdzJ7LI5Bt5E4IBjvAUry"},"fileId":"6eJJSEsgtPJ4jnA9o3/ijn"},"_color":{"__type__":"cc.Color","r":255,"g":242,"b":34},"_contentSize":{"__type__":"cc.Size","width":18.55,"height":35.44},"_trs":{"__type__":"TypedArray","ctor":"Float32Array","array":[12.300000190734863,0,0,0,0,0,1,1,1,1]}},{"__type__":"cc.Node","_name":"bootview","_parent":{"__id__":1},"_children":[{"__id__":9},{"__id__":10}],"_components":[{"__type__":"cc.Layout","node":{"__id__":8},"_layoutSize":{"__type__":"cc.Size","width":224.6,"height":30}},{"__type__":"cc.Widget","node":{"__id__":8},"_alignFlags":4,"_bottom":52.529998779296875}],"_prefab":{"__type__":"cc.PrefabInfo","root":{"__id__":1},"asset":{"__uuid__":"cfdzJ7LI5Bt5E4IBjvAUry"},"fileId":"e2PgNW2fVH8LdRKsHdkPWb"},"_contentSize":{"__type__":"cc.Size","width":224.6,"height":30},"_trs":{"__type__":"TypedArray","ctor":"Float32Array","array":[0,-129.47000122070312,0,0,0,0,1,1,1,1]}},{"__type__":"cc.Node","_name":"bootvalue_title","_parent":{"__id__":8},"_components":[{"__type__":"cc.Label","node":{"__id__":9},"_materials":[{"__uuid__":"ecpdLyjvZBwrvm+cedCcQy"}],"_string":"Point Value:","_N$string":"Point Value:","_fontSize":24,"_lineHeight":24},{"__type__":"cc.LabelOutline","node":{"__id__":9},"_color":{"__type__":"cc.Color","r":45,"g":7,"b":109},"_width":2.6},{"__type__":"cc.Widget","node":{"__id__":9},"_alignFlags":8}],"_prefab":{"__type__":"cc.PrefabInfo","root":{"__id__":1},"asset":{"__uuid__":"cfdzJ7LI5Bt5E4IBjvAUry"},"fileId":"bcIoEnG5RMPa4h9iGEzfJL"},"_color":{"__type__":"cc.Color","r":255,"g":242,"b":34},"_contentSize":{"__type__":"cc.Size","width":132.84,"height":35.44},"_trs":{"__type__":"TypedArray","ctor":"Float32Array","array":[-45.880001068115234,0,0,0,0,0,1,1,1,1]}},{"__type__":"cc.Node","_name":"bootvaluelayout","_parent":{"__id__":8},"_children":[{"__id__":11},{"__id__":12}],"_components":[{"__type__":"cc.Layout","node":{"__id__":10},"_layoutSize":{"__type__":"cc.Size","width":43.15,"height":36},"_resize":1,"_N$layoutType":1,"_N$spacingX":4.6},{"__type__":"cc.Widget","node":{"__id__":10},"alignMode":2,"_alignFlags":32}],"_prefab":{"__type__":"cc.PrefabInfo","root":{"__id__":1},"asset":{"__uuid__":"cfdzJ7LI5Bt5E4IBjvAUry"},"fileId":"13gvcup3hJy6utDDSzW6De"},"_contentSize":{"__type__":"cc.Size","width":43.15,"height":36},"_trs":{"__type__":"TypedArray","ctor":"Float32Array","array":[90.7249984741211,0,0,0,0,0,1,1,1,1]}},{"__type__":"cc.Node","_name":"jinbiimg","_parent":{"__id__":10},"_components":[{"__type__":"cc.Sprite","node":{"__id__":11},"_materials":[{"__uuid__":"ecpdLyjvZBwrvm+cedCcQy"}],"_spriteFrame":{"__uuid__":"85EDehklJElahVe84nelrT"}}],"_prefab":{"__type__":"cc.PrefabInfo","root":{"__id__":1},"asset":{"__uuid__":"cfdzJ7LI5Bt5E4IBjvAUry"},"fileId":"5dJo1bXPhFfJtagwORDcWY"},"_contentSize":{"__type__":"cc.Size","width":20,"height":20},"_trs":{"__type__":"TypedArray","ctor":"Float32Array","array":[-11.574999809265137,0,0,0,0,0,1,1,1,1]}},{"__type__":"cc.Node","_name":"bootvalue","_parent":{"__id__":10},"_components":[{"__type__":"cc.Label","node":{"__id__":12},"_materials":[{"__uuid__":"ecpdLyjvZBwrvm+cedCcQy"}],"_string":"1","_N$string":"1","_fontSize":24,"_lineHeight":24},{"__type__":"cc.LabelOutline","node":{"__id__":12},"_color":{"__type__":"cc.Color","r":45,"g":7,"b":109},"_width":2.6}],"_prefab":{"__type__":"cc.PrefabInfo","root":{"__id__":1},"asset":{"__uuid__":"cfdzJ7LI5Bt5E4IBjvAUry"},"fileId":"88HJHYMvlCU7YmDL4CFO8c"},"_color":{"__type__":"cc.Color","r":255,"g":242,"b":34},"_contentSize":{"__type__":"cc.Size","width":18.55,"height":35.44},"_trs":{"__type__":"TypedArray","ctor":"Float32Array","array":[12.300000190734863,0,0,0,0,0,1,1,1,1]}}]